algotoca/__init__.py
algotoca/grafos/__init__.py
algotoca/grafos/coloracao/__init__.py
algotoca/grafos/coloracao/gulosos.py
algotoca/grafos/coloracao/visual.py
algotoca-0.1.4.6.dist-info/WHEEL
algotoca-0.1.4.6.dist-info/METADATA
algotoca-0.1.4.6.dist-info/RECORD
