Metadata-Version: 2.1
Name: algotoca
Version: 0.1.4.6
Summary: 
Author: WLAraujo
Author-email: lima.wesleyaraujo@gmail.com
Requires-Python: >=3.7,<4.0
Classifier: Programming Language :: Python :: 3
Classifier: Programming Language :: Python :: 3.10
Classifier: Programming Language :: Python :: 3.7
Classifier: Programming Language :: Python :: 3.8
Classifier: Programming Language :: Python :: 3.9
Requires-Dist: cairocffi (>=1.3.0,<2.0.0)
Requires-Dist: igraph (>=0.9.9,<0.10.0)
